{"stats":{"minecraft:crafted":{"minecraft:oak_door":3,"minecraft:oak_planks":176,"minecraft:stone_shovel":2,"minecraft:cooked_chicken":3,"minecraft:furnace":2,"minecraft:spruce_fence":81,"minecraft:cooked_mutton":1,"minecraft:ladder":3,"minecraft:spruce_slab":60,"minecraft:stone_pickaxe":5,"minecraft:chest":2,"minecraft:stone_hoe":1,"minecraft:oak_fence":27,"minecraft:cooked_beef":17,"minecraft:oak_slab":24,"minecraft:cooked_porkchop":17,"minecraft:spruce_planks":212,"minecraft:wooden_pickaxe":2,"minecraft:copper_ingot":8,"minecraft:bucket":2,"minecraft:stone_axe":3,"minecraft:air":0,"minecraft:charcoal":2,"minecraft:stick":172,"minecraft:iron_ingot":53,"minecraft:iron_pickaxe":3,"minecraft:stone_sword":3,"minecraft:spruce_fence_gate":2,"minecraft:torch":68},"minecraft:broken":{"minecraft:wooden_pickaxe":2,"minecraft:stone_pickaxe":1,"minecraft:stone_axe":1},"minecraft:mined":{"minecraft:mossy_cobblestone":1,"minecraft:oak_door":1,"minecraft:spruce_fence":6,"minecraft:grass_block":152,"minecraft:spruce_leaves":13,"minecraft:oxeye_daisy":1,"minecraft:large_fern":1,"minecraft:furnace":2,"minecraft:iron_ore":64,"minecraft:pumpkin":4,"minecraft:azure_bluet":4,"minecraft:potatoes":1,"minecraft:dirt_path":3,"minecraft:oak_stairs":50,"minecraft:stripped_oak_log":16,"minecraft:stone":203,"minecraft:spruce_slab":2,"minecraft:oak_slab":1,"minecraft:glass_pane":1,"minecraft:dandelion":11,"minecraft:oak_fence":1,"minecraft:cornflower":2,"minecraft:crafting_table":5,"minecraft:torch":28,"minecraft:emerald_ore":3,"minecraft:poppy":2,"minecraft:tall_grass":29,"minecraft:copper_ore":2,"minecraft:cobblestone":53,"minecraft:sugar_cane":2,"minecraft:oak_planks":29,"minecraft:diorite":1,"minecraft:blue_bed":3,"minecraft:wall_torch":24,"minecraft:purple_bed":1,"minecraft:sweet_berry_bush":1,"minecraft:wheat":18,"minecraft:spruce_log":87,"minecraft:grass":150,"minecraft:coal_ore":73,"minecraft:oak_log":86,"minecraft:dripstone_block":2,"minecraft:dirt":18,"minecraft:spruce_fence_gate":1,"minecraft:oak_leaves":41,"minecraft:fern":1},"minecraft:picked_up":{"minecraft:wooden_axe":2,"minecraft:crafting_table":5,"minecraft:wheat":14,"minecraft:azure_bluet":4,"minecraft:chicken":3,"minecraft:oak_stairs":47,"minecraft:cornflower":2,"minecraft:string":4,"minecraft:raw_copper":11,"minecraft:bucket":1,"minecraft:beef":17,"minecraft:poppy":1,"minecraft:spruce_slab":2,"minecraft:sugar_cane":5,"minecraft:egg":2,"minecraft:iron_boots":1,"minecraft:furnace":2,"minecraft:raw_iron":64,"minecraft:stick":6,"minecraft:oak_door":1,"minecraft:oak_fence":1,"minecraft:torch":53,"minecraft:spruce_fence":6,"minecraft:porkchop":17,"minecraft:pointed_dripstone":4,"minecraft:diorite":1,"minecraft:stone_sword":1,"minecraft:arrow":6,"minecraft:rotten_flesh":13,"minecraft:cooked_cod":10,"minecraft:mutton":1,"minecraft:cobblestone":404,"minecraft:oxeye_daisy":1,"minecraft:stripped_oak_log":16,"minecraft:feather":4,"minecraft:brown_wool":1,"minecraft:leather":7,"minecraft:potato":27,"minecraft:oak_log":91,"minecraft:gunpowder":2,"minecraft:blue_bed":5,"minecraft:dirt":217,"minecraft:bone":10,"minecraft:apple":1,"minecraft:wheat_seeds":67,"minecraft:iron_ingot":1,"minecraft:oak_planks":56,"minecraft:oak_slab":1,"minecraft:pumpkin":4,"minecraft:sweet_berries":3,"minecraft:dandelion":11,"minecraft:dripstone_block":2,"minecraft:spruce_sapling":1,"minecraft:white_bed":1,"minecraft:spruce_log":84,"minecraft:mossy_cobblestone":1,"minecraft:spruce_fence_gate":1,"minecraft:purple_bed":1,"minecraft:emerald":3,"minecraft:oak_sapling":21,"minecraft:coal":78},"minecraft:dropped":{"minecraft:oak_log":3,"minecraft:stick":3,"minecraft:wooden_axe":2,"minecraft:blue_bed":2,"minecraft:sugar_cane":1,"minecraft:stone_sword":1,"minecraft:oak_planks":11,"minecraft:oak_sapling":8},"minecraft:used":{"minecraft:oak_fence":28,"minecraft:stone_sword":338,"minecraft:spruce_slab":53,"minecraft:stone_shovel":172,"minecraft:ladder":3,"minecraft:chest":2,"minecraft:shield":13,"minecraft:stone_hoe":98,"minecraft:cooked_chicken":3,"minecraft:rotten_flesh":6,"minecraft:oak_door":2,"minecraft:torch":81,"minecraft:dirt":211,"minecraft:spruce_fence":70,"minecraft:wooden_axe":6,"minecraft:oak_stairs":3,"minecraft:furnace":4,"minecraft:oak_sapling":10,"minecraft:cooked_cod":10,"minecraft:cooked_beef":17,"minecraft:potato":27,"minecraft:wheat_seeds":67,"minecraft:water_bucket":10,"minecraft:diorite":1,"minecraft:stone_pickaxe":298,"minecraft:oak_planks":91,"minecraft:wooden_pickaxe":114,"minecraft:spruce_fence_gate":3,"minecraft:blue_bed":2,"minecraft:sugar_cane":4,"minecraft:oak_slab":19,"minecraft:crafting_table":5,"minecraft:white_bed":1,"minecraft:dripstone_block":2,"minecraft:iron_pickaxe":7,"minecraft:stone_axe":317,"minecraft:cobblestone":195,"minecraft:cooked_porkchop":13,"minecraft:bucket":10},"minecraft:custom":{"minecraft:mob_kills":43,"minecraft:interact_with_crafting_table":48,"minecraft:bell_ring":23,"minecraft:leave_game":4,"minecraft:time_since_death":48602,"minecraft:climb_one_cm":3066,"minecraft:sprint_one_cm":543611,"minecraft:walk_one_cm":676117,"minecraft:damage_blocked_by_shield":500,"minecraft:drop":10,"minecraft:talked_to_villager":3,"minecraft:play_time":239073,"minecraft:deaths":7,"minecraft:sneak_time":4330,"minecraft:walk_under_water_one_cm":7111,"minecraft:jump":4080,"minecraft:walk_on_water_one_cm":26171,"minecraft:total_world_time":239073,"minecraft:interact_with_furnace":71,"minecraft:sleep_in_bed":15,"minecraft:time_since_rest":22249,"minecraft:damage_taken":4015,"minecraft:damage_absorbed":563,"minecraft:damage_dealt":6545,"minecraft:swim_one_cm":22435,"minecraft:fly_one_cm":600287,"minecraft:player_kills":1,"minecraft:open_chest":43,"minecraft:crouch_one_cm":9101,"minecraft:fall_one_cm":94964},"minecraft:killed_by":{"minecraft:zombie":1},"minecraft:killed":{"minecraft:spider":2,"minecraft:skeleton":6,"minecraft:chicken":3,"minecraft:pig":9,"minecraft:creeper":1,"minecraft:sheep":1,"minecraft:zombie":13,"minecraft:cow":7}},"DataVersion":3120}